{"0.jpg": [0, 0], "1.jpg": [0, 0], "2.jpg": [1, 1], "3.jpg": [1, 1], "4.jpg": [0, 0], "5.jpg": [0, 0], "6.jpg": [1, 1], "7.png": [1, 1], "8.png": [1, 1], "9.jpg": [0, 0], "10.jpg": [0, 0], "11.jpg": [1, 0], "12.jpg": [0, 0], "13.jpg": [0, 0], "14.jpg": [1, 1], "15.jpg": [0, 0], "16.jpg": [0, 0], "17.jpg": [0, 0], "18.jpg": [0, 0], "19.jpg": [0, 0], "20.jpg": [0, 0], "21.jpg": [0, 0], "22.jpg": [0, 0], "23.png": [1, 1], "24.jpg": [1, 0], "25.jpg": [1, 1], "26.jpg": [1, 1], "27.jpg": [0, 0], "28.jpg": [0, 0], "29.jpg": [1, 1], "30.jpg": [1, 1], "31.jpg": [1, 1], "32.jpg": [0, 0], "33.jpg": [1, 1], "34.jpg": [0, 0], "35.jpg": [0, 0], "36.jpg": [1, 1], "37.jpg": [1, 1], "38.png": [1, 1], "39.jpg": [1, 1], "40.jpg": [1, 1], "41.jpg": [0, 0], "42.jpg": [0, 0], "43.jpg": [0, 0], "44.jpg": [1, 1], "45.jpg": [0, 0], "46.jpg": [1, 1], "47.png": [1, 1], "48.jpg": [0, 0], "49.jpg": [1, 1], "50.jpg": [0, 0], "51.jpg": [0, 0], "52.jpg": [0, 0], "53.png": [1, 1], "54.jpg": [0, 0], "55.jpg": [1, 1], "56.jpg": [0, 0], "57.jpg": [1, 1], "58.jpg": [0, 0], "59.jpg": [0, 0], "60.png": [1, 1], "61.png": [1, 1], "62.jpg": [0, 0], "63.jpg": [0, 0], "64.jpg": [0, 0], "65.jpg": [1, 0], "66.jpg": [0, 0], "67.jpg": [1, 0], "68.jpg": [0, 1], "69.jpg": [0, 0], "70.jpg": [1, 1], "71.png": [1, 1], "72.jpg": [1, 0], "73.png": [1, 1], "74.jpg": [1, 0], "75.png": [1, 1], "76.jpg": [0, 1], "77.jpg": [0, 0], "78.jpg": [0, 0], "79.png": [0, 1], "80.jpg": [1, 0], "81.png": [1, 1], "82.jpg": [0, 1], "83.jpg": [1, 1], "84.jpg": [1, 1], "85.jpg": [0, 0], "86.jpg": [0, 0], "87.jpg": [1, 1], "88.png": [1, 1], "89.png": [1, 1], "90.jpg": [0, 0], "91.jpg": [1, 1], "92.jpg": [0, 0], "93.jpg": [1, 1], "94.png": [1, 1], "95.jpg": [0, 1], "96.jpg": [0, 0], "97.jpg": [0, 0], "98.jpg": [1, 1], "99.jpg": [1, 0], "100.png": [1, 1], "101.jpg": [0, 0], "102.jpg": [0, 0], "103.jpg": [0, 0], "104.png": [1, 1], "105.jpg": [0, 0], "106.jpg": [1, 0], "107.jpg": [1, 0], "108.jpg": [1, 1], "109.jpg": [1, 0], "110.jpg": [0, 0], "111.jpg": [0, 0], "112.jpg": [1, 0], "113.jpg": [0, 0], "114.png": [1, 1], "115.png": [1, 1], "116.jpg": [1, 1], "117.png": [1, 1], "118.jpg": [0, 0], "119.jpg": [0, 0], "120.png": [1, 1], "121.jpg": [0, 1], "122.jpg": [0, 0], "123.jpg": [1, 1], "124.jpg": [0, 0], "125.jpg": [0, 1], "126.jpg": [0, 0], "127.jpg": [0, 0], "128.jpg": [1, 1], "129.jpg": [0, 1], "130.png": [1, 1], "131.jpg": [1, 1], "132.jpg": [0, 0], "133.jpg": [0, 0], "134.png": [0, 1], "135.jpg": [0, 0], "136.jpg": [0, 0], "137.png": [1, 1], "138.jpg": [1, 1], "139.jpg": [0, 0], "140.jpg": [1, 1], "141.jpg": [0, 0], "142.jpg": [0, 0], "143.jpg": [0, 1], "144.png": [1, 1], "145.jpg": [0, 0], "146.jpg": [1, 0], "147.jpg": [0, 0], "148.jpg": [1, 0], "149.jpg": [0, 0], "150.jpeg": [1, 1], "151.jpg": [0, 0], "152.jpg": [0, 0], "153.jpg": [0, 0], "154.jpg": [0, 0], "155.jpeg": [1, 1], "156.jpg": [0, 0], "157.jpg": [0, 0], "158.jpg": [1, 1], "159.jpg": [0, 0], "160.jpg": [0, 0], "161.jpg": [0, 0], "162.jpg": [0, 0], "163.jpg": [0, 0], "164.jpg": [0, 1], "165.jpg": [0, 0], "166.jpg": [1, 1], "167.jpg": [1, 1], "168.png": [1, 1], "169.jpg": [1, 0], "170.jpg": [1, 0], "171.png": [1, 1], "172.jpg": [0, 1], "173.jpg": [0, 0], "174.png": [0, 1], "175.png": [1, 1], "176.jpg": [0, 0], "177.png": [1, 1], "178.jpg": [1, 1], "179.jpg": [0, 0], "180.jpg": [0, 0], "181.jpg": [0, 0], "182.jpg": [1, 0], "183.png": [1, 1], "184.jpg": [1, 1], "185.jpg": [1, 1], "186.jpg": [1, 1], "187.jpg": [0, 0], "188.jpg": [0, 0], "189.jpg": [0, 0], "190.jpg": [0, 0], "191.jpg": [0, 0], "192.png": [0, 1], "193.png": [1, 1], "194.jpg": [1, 1], "195.jpg": [1, 1], "196.jpg": [1, 1], "197.jpg": [0, 0], "198.jpg": [1, 1], "199.jpg": [0, 1], "200.jpg": [0, 1], "201.png": [0, 1], "202.jpg": [0, 0], "203.jpg": [1, 0], "204.jpg": [1, 1], "205.jpg": [0, 0], "206.jpg": [0, 0], "207.jpg": [0, 0], "208.jpg": [0, 0], "209.jpg": [0, 0], "210.png": [1, 1], "211.png": [1, 1], "212.jpg": [0, 0], "213.jpg": [1, 1], "214.jpg": [0, 0], "215.jpg": [1, 0], "216.jpg": [1, 0], "217.jpg": [1, 1], "218.jpg": [1, 1], "219.jpg": [1, 1], "220.jpg": [0, 0], "221.jpg": [0, 0], "222.jpg": [0, 0], "223.jpg": [0, 0], "224.png": [0, 1], "225.png": [1, 1], "226.jpg": [0, 0], "227.jpg": [0, 0], "228.jpeg": [1, 1], "229.jpg": [1, 1], "230.png": [1, 1], "231.jpg": [0, 0], "232.jpg": [1, 1], "233.png": [1, 1], "234.jpg": [1, 1], "235.jpg": [0, 1], "236.png": [1, 1], "237.jpg": [0, 0], "238.jpg": [1, 1], "239.jpg": [1, 1], "240.jpg": [0, 0], "241.jpg": [1, 0], "242.jpg": [0, 0], "243.jpg": [0, 0], "244.jpg": [1, 0], "245.jpg": [0, 0], "246.jpg": [0, 0], "247.jpg": [0, 0], "248.jpg": [1, 1], "249.jpg": [1, 1], "250.jpg": [0, 0], "251.jpg": [0, 1], "252.jpg": [0, 0], "253.jpg": [0, 0], "254.jpg": [1, 1], "255.png": [1, 1], "256.jpg": [1, 1], "257.jpg": [0, 0], "258.jpg": [1, 0], "259.jpg": [1, 1], "260.jpg": [0, 0], "261.jpg": [0, 0], "262.jpg": [1, 1], "263.jpg": [0, 1], "264.jpg": [1, 1], "265.jpg": [0, 0], "266.jpg": [0, 1], "267.jpg": [0, 0], "268.jpg": [1, 1], "269.jpg": [1, 1], "270.jpg": [1, 1], "271.jpg": [0, 0], "272.png": [1, 1], "273.jpg": [0, 0], "274.jpg": [0, 0], "275.jpg": [1, 1], "276.jpg": [0, 0], "277.jpg": [1, 0], "278.png": [0, 1], "279.jpg": [1, 1], "280.jpg": [1, 1], "281.jpg": [0, 1], "282.png": [1, 1], "283.jpg": [1, 1], "284.jpg": [0, 0], "285.jpg": [0, 0], "286.png": [1, 1], "287.jpg": [1, 1], "288.jpg": [0, 0], "289.jpg": [1, 1], "290.jpg": [1, 1], "291.jpg": [0, 0], "292.jpg": [1, 1], "293.png": [1, 1], "294.jpg": [0, 0], "295.jpg": [0, 0], "296.jpg": [0, 1], "297.jpg": [0, 0], "298.jpg": [1, 1], "299.jpg": [0, 0], "300.jpg": [0, 0], "301.png": [1, 1], "302.jpg": [0, 0], "303.jpg": [1, 1], "304.jpg": [0, 0], "305.png": [1, 1], "306.jpg": [0, 0], "307.jpg": [1, 1], "308.jpg": [1, 1], "309.jpg": [0, 1], "310.jpg": [0, 0], "311.jpg": [0, 0], "312.jpg": [0, 0], "313.jpg": [0, 0], "314.jpg": [1, 1], "315.jpg": [1, 1], "316.jpg": [0, 0], "317.jpg": [1, 1], "318.jpg": [0, 0], "319.png": [1, 1], "320.png": [1, 1], "321.jpg": [1, 1], "322.jpg": [0, 0], "323.jpg": [1, 0], "324.jpg": [1, 1], "325.jpg": [0, 0], "326.jpg": [0, 0], "327.png": [1, 1], "328.jpg": [0, 0], "329.jpg": [0, 0], "330.jpg": [0, 0], "331.jpg": [1, 1], "332.png": [1, 1], "333.jpg": [1, 1], "334.jpg": [0, 0], "335.jpg": [0, 1], "336.jpg": [1, 1], "337.jpg": [0, 1], "338.jpg": [0, 0], "339.jpg": [1, 1], "340.jpg": [0, 0], "341.jpg": [0, 0], "342.jpg": [0, 0], "343.jpg": [0, 0], "344.jpg": [1, 0], "345.jpg": [1, 1], "346.png": [1, 1], "347.jpg": [0, 1], "348.png": [1, 1], "349.png": [1, 1], "350.png": [1, 1], "351.jpg": [1, 1], "352.png": [1, 1], "353.jpg": [0, 0], "354.jpg": [0, 0], "355.jpg": [0, 0], "356.jpg": [1, 1], "357.jpg": [0, 0], "358.jpg": [0, 0], "359.jpg": [0, 0], "360.jpg": [0, 0], "361.jpg": [0, 0], "362.jpg": [1, 1], "363.jpg": [0, 0], "364.jpg": [0, 1], "365.jpg": [0, 0], "366.png": [0, 1], "367.jpg": [0, 0], "368.jpg": [1, 1], "369.png": [1, 1], "370.jpg": [1, 1], "371.jpg": [0, 1], "372.jpg": [1, 1], "373.jpg": [1, 1], "374.jpg": [0, 0], "375.jpg": [0, 0], "376.jpg": [0, 0], "377.jpg": [1, 1], "378.png": [1, 1], "379.jpg": [0, 0], "380.jpg": [1, 1], "381.jpg": [0, 0], "382.jpg": [1, 0], "383.jpg": [1, 1], "384.jpg": [1, 1], "385.jpg": [0, 0], "386.png": [1, 1], "387.jpg": [1, 1], "388.jpg": [0, 0], "389.jpg": [0, 0], "390.jpg": [1, 1], "391.png": [1, 1], "392.png": [1, 1], "393.jpg": [1, 1], "394.png": [1, 1], "395.jpg": [0, 0], "396.jpg": [1, 1], "397.jpg": [0, 1], "398.jpg": [0, 0], "399.jpg": [1, 1], "400.png": [1, 1], "401.jpg": [1, 1], "402.jpg": [1, 1], "403.jpg": [0, 0], "404.jpg": [1, 1], "405.png": [1, 1], "406.jpg": [1, 1], "407.jpg": [1, 1], "408.png": [1, 1], "409.jpg": [0, 0], "410.jpg": [0, 1], "411.jpg": [1, 1], "412.png": [1, 1], "413.png": [1, 1], "414.jpg": [0, 0], "415.jpg": [1, 1], "416.jpg": [1, 1], "417.png": [1, 1], "418.jpg": [1, 1], "419.jpg": [0, 0], "420.png": [1, 1], "421.jpg": [0, 0], "422.png": [1, 1], "423.jpg": [0, 0], "424.jpg": [0, 0], "425.jpg": [1, 1], "426.jpg": [1, 1], "427.jpg": [1, 1], "428.png": [1, 1], "429.jpg": [1, 1], "430.jpg": [0, 0], "431.jpg": [1, 1], "432.jpg": [0, 0], "433.png": [1, 1], "434.jpg": [0, 0], "435.jpg": [1, 1], "436.jpg": [0, 0], "437.jpg": [0, 0], "438.jpg": [1, 1], "439.png": [1, 1], "440.jpg": [1, 0], "441.jpg": [0, 0], "442.png": [1, 1], "443.jpg": [1, 1], "444.jpg": [0, 0], "445.jpg": [1, 1], "446.jpg": [0, 0], "447.png": [1, 1], "448.jpg": [0, 0], "449.jpg": [1, 1], "450.jpg": [1, 1], "451.jpg": [0, 0], "452.png": [1, 1], "453.jpg": [0, 0], "454.jpg": [0, 0], "455.jpg": [0, 0], "456.jpg": [0, 0], "457.jpg": [0, 0], "458.jpg": [0, 0], "459.jpg": [0, 0], "460.jpg": [0, 0], "461.png": [1, 1], "462.jpg": [1, 0], "463.jpg": [1, 0], "464.jpg": [0, 0], "465.jpg": [1, 1], "466.jpg": [0, 0], "467.jpg": [0, 0], "468.jpg": [1, 0], "469.jpg": [0, 0], "470.png": [1, 1], "471.jpg": [1, 1], "472.jpg": [0, 0], "473.jpg": [0, 0], "474.jpg": [0, 0], "475.png": [1, 1], "476.jpg": [1, 0], "477.jpg": [0, 0], "478.jpg": [0, 0], "479.png": [0, 1], "480.jpg": [1, 1], "481.jpg": [0, 0], "482.jpg": [0, 0], "483.jpg": [0, 0], "484.jpg": [1, 1], "485.jpg": [0, 1], "486.png": [1, 1], "487.jpg": [0, 0], "488.jpg": [0, 0], "489.jpg": [1, 1], "490.jpg": [1, 1], "491.jpg": [0, 1], "492.png": [1, 1], "493.jpg": [0, 0], "494.png": [0, 1], "495.png": [1, 1], "496.jpg": [1, 1], "497.jpg": [1, 1], "498.jpg": [0, 0], "499.jpg": [1, 1], "500.jpg": [0, 0], "501.jpg": [0, 0], "502.jpg": [0, 1], "503.jpg": [1, 1], "504.jpg": [0, 0], "505.png": [1, 1], "506.jpg": [0, 1], "507.jpg": [1, 1], "508.jpg": [1, 1], "509.png": [0, 1], "510.jpg": [1, 1], "511.jpg": [0, 1], "512.png": [1, 1], "513.png": [0, 1], "514.jpg": [0, 0], "515.png": [1, 1], "516.png": [0, 1], "517.jpg": [0, 0], "518.jpg": [0, 0], "519.jpg": [0, 0], "520.jpg": [0, 0], "521.jpg": [0, 0], "522.png": [1, 1], "523.jpg": [0, 0], "524.jpg": [0, 0], "525.jpg": [0, 0], "526.jpg": [0, 1], "527.png": [1, 1], "528.jpg": [1, 1], "529.jpg": [0, 0], "530.jpg": [1, 1], "531.jpg": [0, 1], "532.jpg": [0, 0], "533.png": [1, 1], "534.png": [1, 1], "535.jpg": [1, 0], "536.jpg": [1, 1], "537.jpg": [0, 1], "538.jpg": [1, 1], "539.jpg": [0, 1], "540.jpg": [0, 0], "541.jpg": [1, 1], "542.jpg": [0, 0], "543.jpg": [0, 0], "544.jpg": [1, 0], "545.jpg": [1, 0], "546.png": [1, 1], "547.png": [1, 1], "548.png": [1, 1], "549.jpg": [0, 0], "550.png": [1, 1], "551.jpg": [1, 1], "552.png": [1, 1], "553.jpg": [0, 0], "554.jpg": [1, 1], "555.jpg": [0, 0], "556.png": [1, 1], "557.jpg": [0, 0], "558.png": [1, 1], "559.jpg": [0, 1], "560.jpg": [1, 1], "561.jpg": [1, 1], "562.jpg": [0, 0], "563.jpg": [0, 0], "564.jpg": [0, 0], "565.png": [1, 1], "566.jpg": [0, 0], "567.jpg": [0, 0], "568.jpg": [0, 0], "569.jpg": [0, 0], "570.jpg": [1, 0], "571.jpg": [1, 1], "572.jpg": [0, 0], "573.jpg": [1, 1], "574.jpg": [0, 0], "575.jpg": [0, 0], "576.jpg": [1, 1], "577.jpg": [1, 1], "578.jpg": [0, 0], "579.png": [1, 1], "580.jpg": [1, 1], "581.jpg": [1, 1], "582.jpg": [0, 1], "583.jpg": [1, 1], "584.jpg": [1, 1], "585.jpg": [0, 0], "586.png": [1, 1], "587.jpg": [0, 0], "588.jpg": [0, 0], "589.jpg": [1, 1], "590.jpg": [1, 1], "591.jpg": [0, 0], "592.jpg": [1, 0], "593.jpg": [0, 0], "594.png": [0, 1], "595.jpg": [1, 0], "596.png": [1, 1], "597.jpg": [1, 0], "598.jpg": [0, 0], "599.jpg": [1, 0], "600.jpg": [0, 0], "601.jpg": [1, 0], "602.png": [1, 1], "603.jpg": [1, 1], "604.jpg": [0, 0], "605.jpg": [0, 1], "606.jpg": [1, 1], "607.jpg": [0, 0], "608.png": [1, 1], "609.jpg": [0, 0], "610.jpg": [1, 1], "611.jpg": [0, 0], "612.jpg": [1, 1], "613.jpg": [0, 0], "614.png": [0, 1], "615.jpg": [1, 1], "616.jpg": [0, 0], "617.png": [1, 1], "618.jpg": [1, 1], "619.jpg": [0, 0], "620.jpg": [0, 0], "621.jpg": [1, 1], "622.png": [1, 1], "623.jpg": [0, 0], "624.png": [1, 1], "625.jpg": [1, 1], "626.jpg": [0, 0], "627.jpg": [1, 1], "628.png": [1, 1], "629.jpg": [0, 0], "630.jpg": [1, 1], "631.jpg": [1, 1], "632.jpg": [0, 0], "633.jpg": [1, 1], "634.jpg": [0, 0], "635.jpg": [0, 0], "636.jpg": [0, 0], "637.jpg": [1, 1], "638.jpg": [0, 0], "639.jpg": [1, 1], "640.jpg": [1, 1], "641.jpg": [0, 0], "642.jpg": [0, 0], "643.jpeg": [0, 1], "644.jpeg": [1, 1], "645.jpg": [0, 0], "646.jpg": [1, 1], "647.png": [1, 1], "648.jpg": [1, 0], "649.jpg": [1, 0], "650.jpg": [1, 1], "651.jpg": [0, 0], "652.jpg": [1, 1], "653.png": [0, 1], "654.png": [1, 1], "655.jpg": [0, 0], "656.jpg": [0, 0], "657.png": [1, 1], "658.jpg": [1, 0], "659.jpg": [1, 1], "660.jpg": [0, 0], "661.jpg": [0, 0], "662.png": [1, 1], "663.jpg": [1, 1], "664.png": [1, 1], "665.png": [1, 1], "666.jpg": [1, 1], "667.jpg": [0, 1], "668.jpg": [0, 0], "669.jpg": [0, 0], "670.jpg": [0, 0], "671.jpg": [1, 1], "672.png": [1, 1], "673.png": [1, 1], "674.jpg": [0, 0], "675.jpg": [1, 1], "676.jpg": [0, 0], "677.jpg": [0, 0], "678.jpg": [0, 0], "679.jpg": [0, 0], "680.jpg": [1, 1], "681.jpg": [1, 1], "682.jpg": [0, 0], "683.jpg": [0, 0], "684.png": [1, 1], "685.jpg": [0, 0], "686.jpg": [0, 0], "687.jpg": [0, 0], "688.jpg": [0, 0], "689.jpg": [1, 0], "690.jpg": [0, 0], "691.jpg": [1, 1], "692.png": [1, 1], "693.jpg": [0, 1], "694.jpg": [0, 0], "695.png": [1, 1], "696.jpg": [1, 0], "697.png": [1, 1], "698.jpg": [1, 1], "699.jpg": [0, 0], "700.jpg": [0, 0], "701.jpg": [1, 1], "702.jpg": [1, 0], "703.jpg": [0, 0], "704.jpg": [1, 0], "705.jpg": [1, 0], "706.jpg": [1, 1], "707.png": [1, 1], "708.jpg": [1, 0], "709.png": [0, 1], "710.jpg": [1, 0], "711.png": [1, 1], "712.jpg": [0, 0], "713.jpg": [1, 1], "714.jpg": [0, 0], "715.jpg": [1, 0], "716.jpg": [0, 1], "717.png": [1, 1], "718.png": [1, 1], "719.jpg": [1, 1], "720.jpg": [0, 1], "721.jpg": [0, 0], "722.jpg": [0, 0], "723.jpg": [0, 0], "724.jpg": [1, 1], "725.jpg": [0, 0], "726.jpg": [1, 1], "727.png": [1, 1], "728.jpg": [0, 0], "729.jpg": [0, 0], "730.jpg": [0, 0], "731.jpg": [1, 1], "732.png": [1, 1], "733.jpg": [0, 0], "734.jpg": [1, 1], "735.jpg": [0, 1], "736.jpg": [1, 1], "737.jpg": [1, 0], "738.jpg": [0, 0], "739.jpg": [1, 1], "740.jpg": [1, 1], "741.jpg": [0, 0], "742.png": [1, 1], "743.png": [1, 1], "744.jpg": [0, 0], "745.jpg": [0, 0], "746.jpg": [0, 0], "747.png": [1, 1], "748.jpg": [1, 1], "749.jpg": [0, 0], "750.png": [1, 1], "751.jpg": [1, 1], "752.jpg": [0, 0], "753.jpg": [0, 0], "754.jpg": [1, 1], "755.jpg": [0, 0], "756.jpg": [0, 0], "757.jpg": [1, 1], "758.jpg": [0, 0], "759.jpg": [1, 1], "760.jpg": [1, 0], "761.jpg": [0, 0], "762.png": [1, 1], "763.jpg": [0, 1], "764.png": [1, 1], "765.jpg": [1, 0], "766.jpg": [0, 0], "767.jpg": [1, 1], "768.jpg": [1, 1], "769.png": [1, 1], "770.jpg": [1, 0], "771.jpg": [0, 0], "772.jpg": [0, 0], "773.jpg": [0, 0], "774.jpg": [1, 0], "775.jpg": [1, 1], "776.jpg": [0, 0], "777.jpg": [0, 0], "778.png": [1, 1], "779.png": [1, 1], "780.jpg": [1, 1], "781.png": [1, 1], "782.jpg": [0, 0], "783.jpg": [0, 0], "784.jpg": [1, 0], "785.jpg": [1, 1], "786.jpg": [1, 1], "787.jpg": [1, 1], "788.jpg": [0, 0], "789.jpg": [0, 0], "790.jpg": [1, 1], "791.png": [1, 1], "792.png": [1, 1], "793.jpg": [1, 1], "794.jpg": [1, 1], "795.png": [1, 1], "796.jpg": [1, 1], "797.jpg": [1, 1], "798.jpg": [1, 0], "799.jpg": [0, 0], "800.jpg": [1, 0], "801.png": [0, 1], "802.jpg": [0, 1], "803.jpg": [0, 0], "804.jpg": [1, 1], "805.png": [1, 1], "806.jpg": [1, 0], "807.jpg": [0, 0], "808.jpg": [0, 0], "809.jpg": [0, 0], "810.png": [1, 1], "811.jpg": [0, 0], "812.jpg": [1, 0], "813.jpg": [0, 0], "814.jpg": [0, 0], "815.jpg": [0, 0], "816.jpg": [1, 1], "817.png": [1, 1], "818.jpg": [1, 0], "819.jpg": [1, 1], "820.jpg": [0, 0], "821.jpg": [0, 0], "822.jpg": [0, 1], "823.png": [1, 1], "824.jpg": [0, 0], "825.jpg": [0, 0], "826.jpg": [1, 1], "827.jpg": [1, 1], "828.jpg": [0, 0], "829.jpg": [0, 0], "830.jpg": [0, 0], "831.jpg": [0, 0], "832.png": [1, 1], "833.jpg": [0, 1], "834.jpg": [1, 1], "835.jpg": [0, 0], "836.jpg": [0, 0], "837.jpg": [0, 0], "838.jpg": [1, 1], "839.jpg": [1, 1], "840.jpg": [1, 1], "841.jpg": [0, 0], "842.jpg": [1, 1], "843.jpg": [0, 0], "844.jpg": [1, 0], "845.png": [1, 1], "846.jpg": [0, 0], "847.png": [1, 1], "848.jpg": [0, 1], "849.jpg": [0, 0], "850.jpg": [1, 1], "851.jpg": [0, 0], "852.jpg": [0, 0], "853.jpg": [1, 0], "854.jpg": [1, 1], "855.jpg": [1, 1], "856.jpg": [0, 0], "857.jpg": [0, 0], "858.jpg": [1, 1], "859.png": [0, 1], "860.png": [1, 1], "861.jpg": [0, 0], "862.png": [1, 1], "863.png": [1, 1], "864.png": [1, 1], "865.jpg": [0, 0], "866.jpg": [1, 1], "867.jpg": [0, 0], "868.jpg": [0, 0], "869.png": [1, 1], "870.png": [1, 1], "871.jpg": [1, 1], "872.jpg": [1, 1], "873.jpg": [0, 0], "874.jpg": [0, 0], "875.jpg": [1, 1], "876.jpg": [1, 1], "877.jpg": [1, 1], "878.png": [1, 1], "879.jpg": [1, 1], "880.jpg": [0, 0], "881.jpg": [0, 0], "882.jpg": [0, 0], "883.jpg": [0, 0], "884.jpg": [0, 0], "885.jpg": [1, 1], "886.jpg": [0, 0], "887.jpg": [1, 0], "888.png": [1, 1], "889.jpg": [1, 1], "890.jpg": [1, 1], "891.jpg": [0, 0], "892.jpg": [1, 1], "893.png": [1, 1], "894.jpg": [1, 1], "895.jpg": [1, 1], "896.jpg": [0, 0], "897.jpg": [1, 0], "898.png": [1, 1], "899.jpg": [0, 1], "900.png": [1, 1], "901.jpg": [1, 1], "902.png": [1, 1], "903.png": [1, 1], "904.jpg": [0, 0], "905.jpg": [1, 1], "906.png": [1, 1], "907.jpg": [0, 0], "908.jpg": [0, 0], "909.jpg": [1, 1], "910.jpg": [0, 0], "911.jpg": [0, 1], "912.jpg": [1, 1], "913.png": [1, 1], "914.jpg": [1, 0], "915.jpg": [0, 1], "916.jpg": [0, 1], "917.jpg": [0, 0], "918.jpg": [1, 1], "919.jpg": [1, 1], "920.jpg": [1, 1], "921.jpg": [0, 0], "922.jpg": [1, 1], "923.jpg": [1, 1], "924.jpg": [0, 0], "925.jpg": [0, 0], "926.png": [0, 1], "927.png": [1, 1], "928.png": [1, 1], "929.jpg": [0, 0], "930.jpg": [1, 0], "931.jpg": [0, 0], "932.jpg": [0, 0], "933.jpg": [0, 0], "934.jpg": [0, 0], "935.jpg": [1, 0], "936.jpg": [0, 0], "937.jpg": [0, 0], "938.jpeg": [1, 1], "939.png": [1, 1], "940.jpg": [1, 1], "941.jpg": [0, 0], "942.jpg": [1, 1], "943.png": [1, 1], "944.jpg": [0, 0], "945.png": [1, 1], "946.jpg": [0, 0], "947.png": [1, 1], "948.jpg": [0, 0], "949.jpg": [1, 0], "950.jpg": [1, 0], "951.png": [1, 1], "952.jpg": [1, 1], "953.jpg": [1, 0], "954.jpg": [1, 1], "955.jpg": [0, 0], "956.jpg": [1, 1], "957.jpg": [0, 1], "958.jpg": [1, 1], "959.jpg": [0, 0], "960.jpg": [0, 0], "961.jpg": [0, 1], "962.png": [1, 1], "963.jpg": [0, 0], "964.jpg": [0, 0], "965.jpg": [0, 0], "966.png": [1, 1], "967.jpg": [1, 0], "968.jpg": [1, 0], "969.jpg": [0, 1], "970.jpg": [0, 1], "971.png": [1, 1], "972.png": [1, 1], "973.png": [1, 1], "974.jpg": [0, 0], "975.jpg": [0, 0], "976.jpg": [0, 0], "977.jpg": [0, 0], "978.jpg": [0, 0], "979.jpg": [1, 0], "980.jpg": [0, 0], "981.jpg": [0, 0], "982.jpg": [0, 0], "983.jpg": [0, 0], "984.jpg": [0, 0], "985.jpg": [0, 0], "986.jpg": [0, 0], "987.jpg": [0, 0], "988.jpg": [1, 0], "989.jpg": [0, 0], "990.jpg": [0, 0], "991.jpg": [0, 0], "992.jpg": [0, 0], "993.jpg": [0, 0], "994.jpg": [0, 0], "995.jpg": [0, 0], "996.jpg": [1, 0], "997.jpg": [0, 0], "998.jpg": [0, 0], "999.jpg": [0, 0]}